{
  "meta": {
    "source_file": "notes/bab-2-4.html",
    "rollout": "gelombang-1"
  },
  "units": [
    {
      "source_id": "bab-2-4-soalan-heading",
      "bm_original": "Bagaimana nasionalisme muncul di Asia Tenggara?",
      "zh_explain": "这道问题引导学生先判断核心概念，再说明历史根据。",
      "key_points_zh": [
        "先锁定题目关键词。",
        "回答时要有立场与证据。"
      ],
      "bm_focus_phrase": "Bagaimana nasionalisme muncul di Asia Tenggara?"
    },
    {
      "source_id": "bab-2-4-soalan-line-1",
      "bm_original": "💡 Di rantau Asia Tenggara, semangat nasionalisme muncul akibat penjajahan Barat.",
      "zh_explain": "这句是对主问题的核心答案，概括本小节最重要的因果与结论。",
      "key_points_zh": [
        "抓住主语、动作与结果。",
        "可用一句话复述大意。"
      ],
      "bm_focus_phrase": "💡 Di rantau Asia Tenggara, semangat nasionalisme muncul akibat penjajahan Barat."
    },
    {
      "source_id": "bab-2-4-fokus-line",
      "bm_original": "Nasionalisme di Asia Tenggara tercetus sebagai reaksi terhadap penjajahan kuasa Barat yang berlaku pada abad ke-19. Subtopik ini meneliti perkembangan nasionalisme di lima negara Asia Tenggara:",
      "zh_explain": "这句说明本课范围与学习路线，帮助学生建立章节地图。",
      "key_points_zh": [
        "先看本节讨论范围。",
        "记住将要展开的重点项目。"
      ],
      "bm_focus_phrase": "Subtopik ini membincangkan"
    },
    {
      "source_id": "bab-2-4-u01",
      "bm_original": "📌 Gerakan ini bertujuan untuk:",
      "zh_explain": "tujuan（目的）——此句列出关键条件，答题须完整呈现所有要点。",
      "key_points_zh": [
        "tujuan = 目的"
      ],
      "bm_focus_phrase": ""
    },
    {
      "source_id": "bab-2-4-u02",
      "bm_original": "📌 Nasionalisme di Filipina bermula untuk menamatkan penjajahan Sepanyol .",
      "zh_explain": "nasionalisme（民族主义）；penjajahan（殖民统治）——此句列出关键条件，答题须完整呈现所有要点。",
      "key_points_zh": [
        "nasionalisme = 民族主义",
        "penjajahan = 殖民统治",
        "penjajah = 殖民者",
        "jajahan = 殖民地"
      ],
      "bm_focus_phrase": ""
    },
    {
      "source_id": "bab-2-4-u03",
      "bm_original": "📌 Matlamat gerakan ini:",
      "zh_explain": "此句列出重要条件或原因，答题时须完整列举。",
      "key_points_zh": [],
      "bm_focus_phrase": ""
    },
    {
      "source_id": "bab-2-4-u04",
      "bm_original": "📌 Aguinaldo bekerjasama dengan Amerika Syarikat dan berjaya mengusir Sepanyol.",
      "zh_explain": "amerika syarikat（美国）；kerjasama（合作）——此句列出关键条件，答题须完整呈现所有要点。",
      "key_points_zh": [
        "amerika syarikat = 美国",
        "kerjasama = 合作"
      ],
      "bm_focus_phrase": ""
    },
    {
      "source_id": "bab-2-4-u05",
      "bm_original": "📌 Golongan nasionalis menukar strategi kepada saluran diplomasi dan politik sederhana.",
      "zh_explain": "strategi（策略）——此句列出关键条件，答题须完整呈现所有要点。",
      "key_points_zh": [
        "strategi = 策略"
      ],
      "bm_focus_phrase": ""
    },
    {
      "source_id": "bab-2-4-u06",
      "bm_original": "📌 Nasionalisme di Burma menentang penjajahan British .",
      "zh_explain": "nasionalisme（民族主义）；penjajahan（殖民统治）——此句列出关键条件，答题须完整呈现所有要点。",
      "key_points_zh": [
        "nasionalisme = 民族主义",
        "penjajahan = 殖民统治",
        "penjajah = 殖民者",
        "british = 英国"
      ],
      "bm_focus_phrase": ""
    },
    {
      "source_id": "bab-2-4-u07",
      "bm_original": "📌 Persatuan Belia Buddha kemudian diambil alih oleh U Ba Pe .",
      "zh_explain": "buddha（佛教）——此句列出关键条件，答题须完整呈现所有要点。",
      "key_points_zh": [
        "buddha = 佛教"
      ],
      "bm_focus_phrase": ""
    },
    {
      "source_id": "bab-2-4-u08",
      "bm_original": "📌 Namanya diubah menjadi Majlis Persatuan Am Kesatuan Burma dan mula memperjuangkan isu bangsa Burma.",
      "zh_explain": "kesatuan（统一）；majlis（理事会）——此句列出关键条件，答题须完整呈现所有要点。",
      "key_points_zh": [
        "kesatuan = 统一",
        "majlis = 理事会",
        "bangsa = 民族"
      ],
      "bm_focus_phrase": ""
    },
    {
      "source_id": "bab-2-4-u09",
      "bm_original": "💡 Keadaan ini meningkatkan tuntutan untuk berkerajaan sendiri.",
      "zh_explain": "kerajaan（政府）；tuntutan（诉求）——此句是本节关键结论，理解这些词汇有助掌握核心论点。",
      "key_points_zh": [
        "kerajaan = 政府",
        "tuntutan = 诉求",
        "raja = 国王"
      ],
      "bm_focus_phrase": ""
    },
    {
      "source_id": "bab-2-4-u10",
      "bm_original": "📌 Golongan Thakin menubuhkan Parti Do Bama Asiayone (Kami Orang Burma).",
      "zh_explain": "hak（权利）——此句列出关键条件，答题须完整呈现所有要点。",
      "key_points_zh": [
        "hak = 权利"
      ],
      "bm_focus_phrase": ""
    },
    {
      "source_id": "bab-2-4-u11",
      "bm_original": "📌 Nasionalisme di Vietnam muncul akibat perubahan sosiopolitik dan sosioekonomi selepas penjajahan Perancis , terutama selepas Perang Dunia Pertama .",
      "zh_explain": "perang dunia pertama（第一次世界大战）；nasionalisme（民族主义）——此句列出关键条件，答题须完整呈现所有要点。",
      "key_points_zh": [
        "perang dunia pertama = 第一次世界大战",
        "nasionalisme = 民族主义",
        "penjajahan = 殖民统治",
        "penjajah = 殖民者"
      ],
      "bm_focus_phrase": ""
    },
    {
      "source_id": "bab-2-4-u12",
      "bm_original": "📌 Pada awalnya, gerakan dipimpin oleh golongan bangsawan dan golongan mandarin yang mahu memulihkan sistem pemerintahan beraja.",
      "zh_explain": "pemerintahan（统治）；bangsawan（贵族）——此句列出关键条件，答题须完整呈现所有要点。",
      "key_points_zh": [
        "pemerintahan = 统治",
        "bangsawan = 贵族",
        "bangsa = 民族",
        "sistem = 制度"
      ],
      "bm_focus_phrase": ""
    },
    {
      "source_id": "bab-2-4-u13",
      "bm_original": "📌 Namun, kepimpinan kemudian diambil alih oleh golongan intelektual muda yang membawa gerakan anti-Perancis.",
      "zh_explain": "kepimpinan（领导力）；perancis（法国）——此句列出关键条件，答题须完整呈现所有要点。",
      "key_points_zh": [
        "kepimpinan = 领导力",
        "perancis = 法国"
      ],
      "bm_focus_phrase": ""
    },
    {
      "source_id": "bab-2-4-u14",
      "bm_original": "📌 Idea nasionalisme disebarkan melalui akhbar seperti:",
      "zh_explain": "nasionalisme（民族主义）——此句列出关键条件，答题须完整呈现所有要点。",
      "key_points_zh": [
        "nasionalisme = 民族主义"
      ],
      "bm_focus_phrase": ""
    },
    {
      "source_id": "bab-2-4-u15",
      "bm_original": "📌 Selepas Perang Dunia Pertama , muncul dua aliran:",
      "zh_explain": "perang dunia pertama（第一次世界大战）；perang（战争）——此句列出关键条件，答题须完整呈现所有要点。",
      "key_points_zh": [
        "perang dunia pertama = 第一次世界大战",
        "perang = 战争"
      ],
      "bm_focus_phrase": ""
    },
    {
      "source_id": "bab-2-4-u16",
      "bm_original": "📌 Nasionalisme di Indonesia bermula daripada isu pendidikan akibat dasar penjajah Belanda .",
      "zh_explain": "nasionalisme（民族主义）；pendidikan（教育）——此句列出关键条件，答题须完整呈现所有要点。",
      "key_points_zh": [
        "nasionalisme = 民族主义",
        "pendidikan = 教育",
        "penjajah = 殖民者",
        "belanda = 荷兰"
      ],
      "bm_focus_phrase": ""
    },
    {
      "source_id": "bab-2-4-u17",
      "bm_original": "📌 Penulisan beliau mendedahkan diskriminasi penjajah Belanda dan kemunduran rakyat Indonesia.",
      "zh_explain": "diskriminasi（歧视）；penulisan（著述）——此句列出关键条件，答题须完整呈现所有要点。",
      "key_points_zh": [
        "diskriminasi = 歧视",
        "penulisan = 著述",
        "penjajah = 殖民者",
        "belanda = 荷兰"
      ],
      "bm_focus_phrase": ""
    },
    {
      "source_id": "bab-2-4-u18",
      "bm_original": "📌 Pertubuhan penting:",
      "zh_explain": "pertubuhan（组织）——此句列出关键条件，答题须完整呈现所有要点。",
      "key_points_zh": [
        "pertubuhan = 组织"
      ],
      "bm_focus_phrase": ""
    },
    {
      "source_id": "bab-2-4-u19",
      "bm_original": "📌 Kemudian muncul parti politik seperti:",
      "zh_explain": "此句列出重要条件或原因，答题时须完整列举。",
      "key_points_zh": [],
      "bm_focus_phrase": ""
    },
    {
      "source_id": "bab-2-4-u20",
      "bm_original": "📌 Thailand berbeza daripada negara lain kerana tidak dijajah oleh Barat.",
      "zh_explain": "此句列出重要条件或原因，答题时须完整列举。",
      "key_points_zh": [],
      "bm_focus_phrase": ""
    },
    {
      "source_id": "bab-2-4-u21",
      "bm_original": "📌 Thailand melaksanakan pemodenan dalam:",
      "zh_explain": "此句列出重要条件或原因，答题时须完整列举。",
      "key_points_zh": [],
      "bm_focus_phrase": ""
    },
    {
      "source_id": "bab-2-4-u22",
      "bm_original": "📌 Raja Mongkut membawa masuk 80 orang penasihat Barat untuk melatih pegawai tempatan.",
      "zh_explain": "raja（国王）——此句列出关键条件，答题须完整呈现所有要点。",
      "key_points_zh": [
        "raja = 国王"
      ],
      "bm_focus_phrase": ""
    },
    {
      "source_id": "bab-2-4-u23",
      "bm_original": "📌 Pemerintahan Raja Vajiravudh yang lemah mencetuskan ketidakpuasan rakyat.",
      "zh_explain": "pemerintahan（统治）；raja（国王）——此句列出关键条件，答题须完整呈现所有要点。",
      "key_points_zh": [
        "pemerintahan = 统治",
        "raja = 国王"
      ],
      "bm_focus_phrase": ""
    },
    {
      "source_id": "bab-2-4-u24",
      "bm_original": "📌 Politik negara lebih dikuasai oleh kerabat diraja Thailand.",
      "zh_explain": "raja（国王）——此句列出关键条件，答题须完整呈现所有要点。",
      "key_points_zh": [
        "raja = 国王"
      ],
      "bm_focus_phrase": ""
    },
    {
      "source_id": "bab-2-4-u25",
      "bm_original": "📌 Golongan reformis menubuhkan Parti Rakyat yang dipimpin oleh:",
      "zh_explain": "此句列出重要条件或原因，答题时须完整列举。",
      "key_points_zh": [],
      "bm_focus_phrase": ""
    },
    {
      "source_id": "bab-2-4-u26",
      "bm_original": "📌 Rakyat tidak puas hati dengan penguasaan ekonomi oleh kapitalis Barat dan orang Cina.",
      "zh_explain": "penguasaan（统治）；ekonomi（经济）——此句列出关键条件，答题须完整呈现所有要点。",
      "key_points_zh": [
        "penguasaan = 统治",
        "ekonomi = 经济",
        "itali = 意大利",
        "cina = 华人"
      ],
      "bm_focus_phrase": ""
    },
    {
      "source_id": "bab-2-4-u27",
      "bm_original": "💡 Pengajaran: Sumbangan pemimpin nasionalisme perlu diteladani sebagai inspirasi mempertahankan kedaulatan bangsa dan negara.",
      "zh_explain": "nasionalisme（民族主义）；kedaulatan（主权）——此句是本节关键结论，理解这些词汇有助掌握核心论点。",
      "key_points_zh": [
        "nasionalisme = 民族主义",
        "kedaulatan = 主权",
        "pemimpin = 领导人",
        "bangsa = 民族"
      ],
      "bm_focus_phrase": ""
    },
    {
      "source_id": "bab-2-4-u28",
      "bm_original": "🌏 Di Asia Tenggara , semangat nasionalisme muncul akibat penjajahan Barat.",
      "zh_explain": "nasionalisme（民族主义）；penjajahan（殖民统治）",
      "key_points_zh": [
        "nasionalisme = 民族主义",
        "penjajahan = 殖民统治",
        "penjajah = 殖民者",
        "semangat = 精神"
      ],
      "bm_focus_phrase": ""
    },
    {
      "source_id": "bab-2-4-u29",
      "bm_original": "⚔️ Gerakan ini bertujuan membebaskan negara daripada penjajahan, mempertahankan kedaulatan dan membina jati diri bangsa.",
      "zh_explain": "kedaulatan（主权）；penjajahan（殖民统治）",
      "key_points_zh": [
        "kedaulatan = 主权",
        "penjajahan = 殖民统治",
        "penjajah = 殖民者",
        "jajahan = 殖民地"
      ],
      "bm_focus_phrase": ""
    },
    {
      "source_id": "bab-2-4-u30",
      "bm_original": "📍 Perkembangan nasionalisme dapat dilihat di Filipina , Burma , Vietnam dan Indonesia .",
      "zh_explain": "nasionalisme（民族主义）；perkembangan（发展）",
      "key_points_zh": [
        "nasionalisme = 民族主义",
        "perkembangan = 发展"
      ],
      "bm_focus_phrase": ""
    },
    {
      "source_id": "bab-2-4-u31",
      "bm_original": "🛡️ Thailand pula melaksanakan pembaharuan untuk mengekalkan kemerdekaannya daripada penjajahan Barat.",
      "zh_explain": "kemerdekaan（独立）；penjajahan（殖民统治）",
      "key_points_zh": [
        "kemerdekaan = 独立",
        "penjajahan = 殖民统治",
        "penjajah = 殖民者",
        "jajahan = 殖民地"
      ],
      "bm_focus_phrase": ""
    }
  ]
}